cloudflare_ddns_updater/__init__.py
cloudflare_ddns_updater/constants.py
cloudflare_ddns_updater/initializer.py
cloudflare_ddns_updater/ip_updater.py
cloudflare_ddns_updater-1.0.5.dist-info/licenses/LICENSE
tests/__init__.py
tests/leo.py
tests/testapi.py
cloudflare_ddns_updater-1.0.5.dist-info/METADATA
cloudflare_ddns_updater-1.0.5.dist-info/WHEEL
cloudflare_ddns_updater-1.0.5.dist-info/entry_points.txt
cloudflare_ddns_updater-1.0.5.dist-info/top_level.txt
cloudflare_ddns_updater-1.0.5.dist-info/RECORD
