Metadata-Version: 2.4
Name: cloudflare-ddns-updater
Version: 1.0.5
Summary: A Python tool to update Cloudflare DNS automatically using DDNS.
Home-page: https://github.com/robgst/cloudflare-ddns-updater
Author: Roberto Giusti
Author-email: rgiusti@gmail.com
Classifier: Programming Language :: Python :: 3
Classifier: License :: OSI Approved :: MIT License
Requires-Python: >=3.10
License-File: LICENSE
Requires-Dist: requests>=2.32.4
Requires-Dist: python-crontab
Requires-Dist: setuptools>=78.1.1
Dynamic: author
Dynamic: author-email
Dynamic: classifier
Dynamic: description
Dynamic: description-content-type
Dynamic: home-page
Dynamic: license-file
Dynamic: requires-dist
Dynamic: requires-python
Dynamic: summary
